LICENSE.mit
MANIFEST.in
README.md
setup.py
PyMarvel.egg-info/PKG-INFO
PyMarvel.egg-info/SOURCES.txt
PyMarvel.egg-info/dependency_links.txt
PyMarvel.egg-info/requires.txt
PyMarvel.egg-info/top_level.txt
PyMarvel.egg-info/zip-safe
marvel/__init__.py
marvel/character.py
marvel/comic.py
marvel/config.py
marvel/core.py
marvel/creator.py
marvel/event.py
marvel/marvel.py
marvel/series.py
marvel/story.py
marvel/tests.py