Metadata-Version: 1.0
Name: PyMarvel
Version: 0.1.0
Summary: Python wrapper for Marvel API
Home-page: http://github.com/gpennington/PyMarvel
Author: Garrett Pennington
Author-email: garrettp@gmail.com
License: MIT
Keywords: marvel api comics python
Platform: UNKNOWN
Classifier: Development Status :: 1 - Planning
Classifier: Environment :: Console
Classifier: Intended Audience :: Developers
Classifier: Natural Language :: English
Classifier: Operating System :: OS Independent
Classifier: Programming Language :: Python
Classifier: Topic :: Internet :: WWW/HTTP :: Dynamic Content :: CGI Tools/Libraries
Classifier: Topic :: Utilities
Classifier: License :: OSI Approved :: MIT License
